neuroimager/__init__.py
neuroimager/pipes/__init__.py
neuroimager/pipes/brainage.py
neuroimager/pipes/cca.py
neuroimager/pipes/decoder.py
neuroimager/pipes/explore.py
neuroimager/pipes/graph.py
neuroimager/pipes/hmm.py
neuroimager/pipes/task_fmri.py
neuroimager/plotting/__init__.py
neuroimager/plotting/decompose.py
neuroimager/plotting/plot.py
neuroimager/plotting/styler.py
neuroimager/plotting/surf_plotting.py
neuroimager/preproc/__init__.py
neuroimager/preproc/decompose.py
neuroimager/preproc/prep.py
neuroimager/stats/__init__.py
neuroimager/stats/correlation.py
neuroimager/stats/perm_ttest.py
neuroimager/utils/__init__.py
neuroimager/utils/atlas.py
neuroimager/utils/fc.py
neuroimager/utils/ml.py
neuroimager/utils/rbload.py
neuroimager-0.1.3.dist-info/LICENSE
neuroimager-0.1.3.dist-info/METADATA
neuroimager-0.1.3.dist-info/WHEEL
neuroimager-0.1.3.dist-info/top_level.txt
neuroimager-0.1.3.dist-info/RECORD
