Metadata-Version: 2.1
Name: neuroimager
Version: 0.1.3
Summary: A collection of utilities used for MRI data analysis
Home-page: https://github.com/Wetiqe/neuroimager
Author: Wetiqe
Author-email: jzni132134@gmail.com
Classifier: Development Status :: 1 - Planning
Classifier: Programming Language :: Python :: 3
Classifier: Programming Language :: Python :: 3.6
Classifier: Programming Language :: Python :: 3.7
Classifier: Programming Language :: Python :: 3.8
Classifier: Programming Language :: Python :: 3.9
Classifier: Programming Language :: Python :: 3.10
License-File: LICENSE
Requires-Dist: matplotlib
Requires-Dist: numpy
Requires-Dist: pandas
Requires-Dist: scipy
Requires-Dist: pingouin
Requires-Dist: seaborn
Requires-Dist: scikit-learn
Requires-Dist: nilearn
Requires-Dist: networkx
Requires-Dist: munkres
Requires-Dist: scikit-network
Requires-Dist: pybids
Requires-Dist: tqdm
Provides-Extra: decoder
Requires-Dist: neuromaps ; extra == 'decoder'
Requires-Dist: nimare ; extra == 'decoder'
Provides-Extra: torch
Requires-Dist: torch >=1.0.0 ; extra == 'torch'
